{
    "swagger": "2.0",
    "info": {
        "description": "This is the v1 of the API",
        "title": "Example API v1",
        "contact": {},
        "version": "1.0"
    },
    "basePath": "/api/v1",
    "paths": {
        "/healthz": {
            "get": {
                "tags": [
                    "internal"
                ],
                "summary": "Health check status",
                "responses": {
                    "200": {
                        "description": "OK"
                    },
                    "500": {
                        "description": "Internal Server Error"
                    }
                }
            }
        },
        "/hello": {
            "get": {
                "tags": [
                    "internal"
                ],
                "summary": "test api",
                "responses": {
                    "200": {
                        "description": "OK"
                    },
                    "500": {
                        "description": "Internal Server Error"
                    }
                }
            }
        }
    }
}